context_async_sqlalchemy/__init__.py
context_async_sqlalchemy/auto_commit.py
context_async_sqlalchemy/connect.py
context_async_sqlalchemy/context.py
context_async_sqlalchemy/session.py
context_async_sqlalchemy/fastapi_utils/__init__.py
context_async_sqlalchemy/fastapi_utils/middleware.py
context_async_sqlalchemy-1.2.0.dist-info/METADATA
context_async_sqlalchemy-1.2.0.dist-info/WHEEL
context_async_sqlalchemy-1.2.0.dist-info/licenses/LICENSE
context_async_sqlalchemy-1.2.0.dist-info/RECORD
