Metadata-Version: 2.4
Name: context-async-sqlalchemy
Version: 1.2.0
Summary: A convenient way to configure and interact with a async sqlalchemy session through context in asynchronous applications
Project-URL: Homepage, https://github.com/krylosov-aa/context-async-sqlalchemy
Author-email: krylosov-aa <krylosov.andrew@gmail.com>
License: MIT
License-File: LICENSE
Requires-Python: >=3.9
Requires-Dist: sqlalchemy>=2.0
